metobs_gui/__init__.py
metobs_gui/analysis_page.py
metobs_gui/basic_fig.ui
metobs_gui/data_func.py
metobs_gui/errors.py
metobs_gui/extra_windows.py
metobs_gui/fig_window.ui
metobs_gui/figuremodel.py
metobs_gui/fill_page.py
metobs_gui/gui_settings_page.py
metobs_gui/html_map.ui
metobs_gui/import_data_page.py
metobs_gui/json_save_func.py
metobs_gui/log_displayer.py
metobs_gui/main.py
metobs_gui/mainwindow.ui
metobs_gui/metadata_page.py
metobs_gui/modeldata_fig_window.ui
metobs_gui/modeldata_page.py
metobs_gui/pandasmodel.py
metobs_gui/path_handler.py
metobs_gui/qc_page.py
metobs_gui/save_gui_vals.json
metobs_gui/tabular_data_window.ui
metobs_gui/template_func.py
metobs_gui/template_page.py
metobs_gui/tlk_scripts.py
metobs_gui/tmp/metadata_html.html
metobs_gui-0.0.1a0.dist-info/LICENSE
metobs_gui-0.0.1a0.dist-info/METADATA
metobs_gui-0.0.1a0.dist-info/WHEEL
metobs_gui-0.0.1a0.dist-info/RECORD
